{"WL":[{"cost":9,"server":0,"client":7,"graphic":1,"sound":1,"name":"김다온","img_name":"worker_104","talent":["월급루팡","마법사"]},{"cost":15,"server":9,"client":9,"graphic":8,"sound":9,"name":"황시영","img_name":"worker_051","talent":["커플B","틱토커"]},{"cost":11,"server":0,"client":9,"graphic":3,"sound":5,"name":"조진서","img_name":"worker_022","talent":["라이트맨","종달새"]},{"cost":3,"server":2,"client":9,"graphic":4,"sound":6,"name":"서세현","img_name":"worker_070","talent":["대학원생"]},{"cost":6,"server":2,"client":10,"graphic":0,"sound":4,"name":"유민선","img_name":"worker_090","talent":["탱커","슬로우 스타터","히키코모리"]},{"cost":1,"server":9,"client":0,"graphic":9,"sound":9,"name":"조윤호","img_name":"worker_107","talent":["에너자이저","대학원생","고양이"]},{"cost":6,"server":0,"client":4,"graphic":7,"sound":3,"name":"남서빈","img_name":"worker_000","talent":["커플A"]},{"cost":12,"server":7,"client":6,"graphic":9,"sound":7,"name":"박준원","img_name":"worker_084","talent":["아싸시노","커플B","거주자"]}],"server":29,"client":54,"graphic":41,"sound":44,"cost":437}